cmddocgen/__init__.py
cmddocgen/cli.py
cmddocgen/cmd_doc_gen.py
cmddocgen/llm.py
cmddocgen-0.1.0.dist-info/licenses/LICENSE
cmddocgen-0.1.0.dist-info/METADATA
cmddocgen-0.1.0.dist-info/WHEEL
cmddocgen-0.1.0.dist-info/entry_points.txt
cmddocgen-0.1.0.dist-info/top_level.txt
cmddocgen-0.1.0.dist-info/RECORD
