Metadata-Version: 2.4
Name: cmddocgen
Version: 0.1.0
Summary: CmdDocGen - Universal command line help information extraction and man page generation tool powered by LLM for intelligent subcommand analysis
Home-page: https://github.com/2niuhe/CmdDocGen
Author: Carlton Tang
Author-email: Carlton <carlton2tang@gmail.com>
Project-URL: Homepage, https://github.com/2niuhe/CmdDocGen
Project-URL: Documentation, https://github.com/2niuhe/CmdDocGen#readme
Project-URL: Issues, https://github.com/2niuhe/CmdDocGen/issues
Classifier: Development Status :: 3 - Alpha
Classifier: Intended Audience :: Developers
Classifier: Intended Audience :: System Administrators
Classifier: Programming Language :: Python :: 3
Classifier: Topic :: Software Development :: Documentation
Classifier: Topic :: System :: Systems Administration
Classifier: Topic :: Utilities
Requires-Python: >=3.8
License-File: LICENSE
Requires-Dist: openai>=1.0.0
Requires-Dist: python-dotenv>=0.20.0
Dynamic: author
Dynamic: home-page
Dynamic: license-file
Dynamic: requires-python
